{
    "buttons": {
		"AddElement": "Add",
		"Refresh": "Refresh",
		"Close": "Close",
		"Rename": "Rename",
		"Delete": "Delete",
		"Save": "Save",
		"Cancel": "Cancel",
		"Create": "Create",
		"AddProcess": "Add diagram",
		"AddFolder": "Add folder",
		"Import": "Import",
		"Deploy": "Deploy",
		"Copy": "Add by sample",
        "Select": "Select",
        "SetupMaterial": "Setup material",
        "TakeToWork": "Take to work",
        "Pause": "Pause",
        "Downtime": "Downtime",
        "RemoveAllParties": "Remove all parties",
        "ScanQRCode": "Scan QR code",
        "ComeBack": "Come back",
        "MyProduction": "My production",
        "ProductionOfTheCurrentWorkCenter": "Production of the current Work Center",
        "Fixate": "Fixate",
        "DeleteInstallation": "Delete installation",
        "WriteOffMaterials": "Write off materials",
        "PrintProduction": "Print production",
        "DeleteProduction": "Delete production"
    },
    "tabs": {
        "InPlan": "In plan",
        "Done": "Done"
    },
    "placeholders": {
        "SearchMaterial": "Specify the QR batch of material to install",
        "SearchDocument": "Documents search",
        "SearchTask": "Task search"
    },
    "labels": {
        "WorkCenter": "Work Center",
        "NoWorkCenter": "No work center",
        "FixOnWorkCenter": "Fix on Work Center",
        "DowntimeFixation": "Downtime fixation",
        "SelectWorkCenterToCommit": "Select Work Center to commit",
        "AbsentInstalledParties": "Absent installed parties",
        "NoFactOfRegistration": "There is no fact of registration production per shift",
        "DownloadDowntimes": "Download downtimes",
        "NoDowntime": "No downtime",
        "DownloadDocuments": "Download documents",
        "NoDocuments": "No documents",
        "NoTasks": "No tasks",
        "Name": "Name",
        "Code": "Code",
		"Designer": "Designer",
        "Preview": "Preview",
        "DisplayType": "Display type",
        "FormContructor": "Form constructor"
    },
    "dialogs": {
        "Yes": "Yes",
        "No": "No",
        "WorkCenterChange": "Work Center Change",
        "SwitchToAnotherTask": "Are you sure you want to switch to another task?",
        "DeleteInstallation": "Are you sure you want to delete the batch installed on the work center?",
        "DeleteProduction": "Are you sure you want to remove the production?",
        "RegistrationProduction": "Registration production",
        "RegistrationDowntime": "Registration downtime",
        "RegistrationDocument": "Registration document"

    },
    "cards": {
        "Cause": "Cause",
        "Start": "Start",
        "End": "End",
        "Comment": "Comment",
        "WriteOff": "Write-off"
    },
    "formioForm": {
        "complete": "Submission Complete",
        "error": "Please fix the following errors before submitting.",
        "required": "{{field}} is required",
        "pattern": "{{field}} does not match the pattern {{pattern}}",
        "minLength": "{{field}} must be longer than {{length}} characters.",
        "maxLength": "{{field}} must be shorter than {{length}} characters.",
        "minWords": "{{field}} must have more than {{length}} words.",
        "maxWords": "{{field}} must have less than {{length}} words.",
        "min": "{{field}} cannot be less than {{min}}.",
        "max": "{{field}} cannot be greater than {{max}}.",
        "maxDate": "{{field}} should not contain date after {{- maxDate}}",
        "minDate": "{{field}} should not contain date before {{- minDate}}",
        "invalid_email": "{{field}} must be a valid email.",
        "invalid_url": "{{field}} must be a valid url.",
        "invalid_regex": "{{field}} does not match the pattern {{regex}}.",
        "invalid_date": "{{field}} is not a valid date.",
        "invalid_day": "{{field}} is not a valid day.",
        "mask": "{{field}} does not match the mask.",
        "stripe": "{{stripe}}",
        "month": "Month",
        "day": "Day",
        "year": "Year",
        "january": "January",
        "february": "February",
        "march": "March",
        "april": "April",
        "may": "May",
        "june": "June",
        "july": "July",
        "august": "August",
        "september": "September",
        "october": "October",
        "november": "November",
        "december": "December",
        "next": "Next",
        "previous": "Previous",
        "cancel": "Cancel",
        "submit": "Submit Form",
        "Type to search" : "Type to search"
    },
    "errors": {
        "InitializeSignalR": "Failed initialize SignalR",
        "InputCodeForm": "Input code form",
        "RequiredInputField": "Field is required",
        "loginError": "Login failed for this code"
    }
}